nullability/__init__.py
nullability-0.1.1.dist-info/METADATA
nullability-0.1.1.dist-info/WHEEL
nullability-0.1.1.dist-info/licenses/LICENSE
nullability-0.1.1.dist-info/RECORD
