Metadata-Version: 2.1
Name: nullability
Version: 0.1.1
Summary: Pass nullable arguments that may not exist
Project-URL: Homepage, https://github.com/sayanarijit/nullablility
Author-email: Arijit Basu <sayanarijit@gmail.com>
Maintainer-email: Arijit Basu <sayanarijit@gmail.com>
License: MIT License
License-File: LICENSE
Classifier: Development Status :: 3 - Alpha
Classifier: Intended Audience :: Developers
Classifier: License :: OSI Approved :: MIT License
Classifier: Programming Language :: Python :: 3
Classifier: Programming Language :: Python :: 3.7
Classifier: Programming Language :: Python :: 3.8
Classifier: Programming Language :: Python :: 3.9
Classifier: Programming Language :: Python :: 3.10
Classifier: Programming Language :: Python :: 3.11
Requires-Python: >=3.7
Provides-Extra: test
Requires-Dist: flake8; extra == 'test'
Requires-Dist: pytest; extra == 'test'
Requires-Dist: pytest-cov; extra == 'test'
